django_health_checker-0.1.dist-info/DESCRIPTION.rst
django_health_checker-0.1.dist-info/METADATA
django_health_checker-0.1.dist-info/RECORD
django_health_checker-0.1.dist-info/WHEEL
django_health_checker-0.1.dist-info/metadata.json
django_health_checker-0.1.dist-info/top_level.txt
health_checker/__init__.py
health_checker/urls.py
health_checker/views.py
