Metadata-Version: 2.0
Name: django-health-checker
Version: 0.1
Summary: A simple Django app to conduct health checks.
Home-page: UNKNOWN
Author: Omri Dagan
Author-email: omritoptix@gmail.com
License: BSD License
Platform: UNKNOWN
Requires-Dist: django-health-check (==3.5.0)
